doc_search/__init__.py
doc_search/async_docs.py
doc_search/sync_docs.py
doc_search/utils.py
doc_search-1.0.7.dist-info/LICENSE
doc_search-1.0.7.dist-info/METADATA
doc_search-1.0.7.dist-info/WHEEL
doc_search-1.0.7.dist-info/top_level.txt
doc_search-1.0.7.dist-info/zip-safe
doc_search-1.0.7.dist-info/RECORD
