Metadata-Version: 2.1
Name: doc-search
Version: 1.0.7
Summary: A package for searching documentation built with sphinx
Home-page: https://github.com/Tom-the-Bomb/doc-search
Author: Tom-the-Bomb
License: MIT
Project-URL: Repository, https://github.com/Tom-the-Bomb/doc-search
Project-URL: Issue tracker, https://github.com/Tom-the-Bomb/doc-search/issues
Platform: UNKNOWN
Classifier: Intended Audience :: Developers
Classifier: Programming Language :: Python
Classifier: Natural Language :: English
Classifier: Programming Language :: Python :: 3.7
Classifier: Programming Language :: Python :: 3.8
Classifier: Programming Language :: Python :: 3.9
Classifier: Topic :: Software Development :: Libraries
Classifier: Topic :: Software Development :: Libraries :: Python Modules
Classifier: Topic :: Utilities
Requires-Python: >=3.7
Requires-Dist: aiohttp
Requires-Dist: requests
